helloworld_apar/__init__.py
helloworld_apar/helloworld.py
helloworld_apar_pkg-0.0.3.dist-info/LICENSE.txt
helloworld_apar_pkg-0.0.3.dist-info/METADATA
helloworld_apar_pkg-0.0.3.dist-info/WHEEL
helloworld_apar_pkg-0.0.3.dist-info/top_level.txt
helloworld_apar_pkg-0.0.3.dist-info/RECORD
