Metadata-Version: 2.1
Name: helloworld-apar-pkg
Version: 0.0.3
Summary: Say hello!
Home-page: https://github.com/AparGarg99/helloworldpypi
Author: Apar Garg
Author-email: aparworkstuff@gmail.com
License: UNKNOWN
Platform: UNKNOWN
Classifier: Programming Language :: Python :: 3
Classifier: Programming Language :: Python :: 3.7
Classifier: Programming Language :: Python :: 3.8
Classifier: License :: OSI Approved :: GNU General Public License v2 or later (GPLv2+)
Classifier: Operating System :: OS Independent
License-File: LICENSE.txt
Requires-Dist: tqdm (~=4.64.1)
